etlportfolio/__init__.py
etlportfolio/data.py
etlportfolio/portfolio.py
etlportfolio/optimized/__init__.py
etlportfolio/optimized/risk_criteria.cpython-310-x86_64-linux-gnu.so
tests/__init__.py
tests/test_data.py
tests/test_portfolio.py
etlportfolio-2.0.4.dist-info/LICENSE
etlportfolio-2.0.4.dist-info/METADATA
etlportfolio-2.0.4.dist-info/WHEEL
etlportfolio-2.0.4.dist-info/top_level.txt
etlportfolio-2.0.4.dist-info/RECORD
