Metadata-Version: 2.1
Name: etlportfolio
Version: 2.0.4
Summary: Expected tail loss portfolio optimisation in python
Home-page: https://github.com/jamesjtobin/etlportfolio
Author: Jack Tobin
Author-email: tobjack330@gmail.com
Project-URL: Bug Tracker, https://github.com/jamesjtobin/etlportfolio/issues
Classifier: Programming Language :: Python :: 3
Classifier: License :: OSI Approved :: MIT License
Classifier: Operating System :: Microsoft :: Windows :: Windows 11
Requires-Python: >=3.10
License-File: LICENSE
Requires-Dist: yfinance
Requires-Dist: pandas
Requires-Dist: numpy
Requires-Dist: seaborn
Requires-Dist: matplotlib
Requires-Dist: scipy
